gavelgen/__init__.py
gavelgen/gavel.py
gavelgen/pearwise.py
pearwise/__init__.py
pearwise/pearwise.py
pearwise-0.1.3.dist-info/METADATA
pearwise-0.1.3.dist-info/WHEEL
pearwise-0.1.3.dist-info/top_level.txt
pearwise-0.1.3.dist-info/RECORD
