Metadata-Version: 2.1
Name: pearwise
Version: 0.1.3
Summary: PearWiseAI SDK to log and score interactions
Author: pearwise
Author-email: hello@pearwise.com
Requires-Dist: requests
Requires-Dist: pydantic
